[
    {
        "key": "dbln",
        "value": "%7B%2261572414788764%22%3A%22PDinqGWt%22%2C%22100083402901153%22%3A%22okctuzvP%22%7D",
        "domain": "facebook.com",
        "path": "/login/device-based/",
        "hostOnly": false,
        "creation": "2025-07-30T13:45:06.945Z",
        "lastAccessed": "2025-07-30T13:45:06.948Z"
    },
    {
        "key": "datr",
        "value": "9X-CaL23Wj-EDtYvi0A1rMhc",
        "domain": "facebook.com",
        "path": "/",
        "hostOnly": false,
        "creation": "2025-07-30T13:45:06.948Z",
        "lastAccessed": "2025-07-30T13:45:06.948Z"
    },
    {
        "key": "sb",
        "value": "9X-CaExJ7psn0Qh2_NNDH369",
        "domain": "facebook.com",
        "path": "/",
        "hostOnly": false,
        "creation": "2025-07-30T13:45:06.948Z",
        "lastAccessed": "2025-07-30T13:45:06.948Z"
    },
    {
        "key": "vpd",
        "value": "v1%3B746x393x2.75",
        "domain": "facebook.com",
        "path": "/",
        "hostOnly": false,
        "creation": "2025-07-30T13:45:06.948Z",
        "lastAccessed": "2025-07-30T13:45:06.948Z"
    },
    {
        "key": "ps_l",
        "value": "1",
        "domain": "facebook.com",
        "path": "/",
        "hostOnly": false,
        "creation": "2025-07-30T13:45:06.948Z",
        "lastAccessed": "2025-07-30T13:45:06.948Z"
    },
    {
        "key": "ps_n",
        "value": "1",
        "domain": "facebook.com",
        "path": "/",
        "hostOnly": false,
        "creation": "2025-07-30T13:45:06.948Z",
        "lastAccessed": "2025-07-30T13:45:06.948Z"
    },
    {
        "key": "locale",
        "value": "en_GB",
        "domain": "facebook.com",
        "path": "/",
        "hostOnly": false,
        "creation": "2025-07-30T13:45:06.948Z",
        "lastAccessed": "2025-07-30T13:45:06.948Z"
    },
    {
        "key": "pas",
        "value": "61572414788764%3AfR35k6k6IJ%2C100083402901153%3AqAi9xpXnKH",
        "domain": "facebook.com",
        "path": "/",
        "hostOnly": false,
        "creation": "2025-07-30T13:45:06.948Z",
        "lastAccessed": "2025-07-30T13:45:06.948Z"
    },
    {
        "key": "dpr",
        "value": "3.0234789848327637",
        "domain": "facebook.com",
        "path": "/",
        "hostOnly": false,
        "creation": "2025-07-30T13:45:06.948Z",
        "lastAccessed": "2025-07-30T13:45:06.948Z"
    },
    {
        "key": "m_pixel_ratio",
        "value": "2.75",
        "domain": "facebook.com",
        "path": "/",
        "hostOnly": false,
        "creation": "2025-07-30T13:45:06.948Z",
        "lastAccessed": "2025-07-30T13:45:06.948Z"
    },
    {
        "key": "wd",
        "value": "393x876",
        "domain": "facebook.com",
        "path": "/",
        "hostOnly": false,
        "creation": "2025-07-30T13:45:06.948Z",
        "lastAccessed": "2025-07-30T13:45:06.948Z"
    },
    {
        "key": "c_user",
        "value": "100083402901153",
        "domain": "facebook.com",
        "path": "/",
        "hostOnly": false,
        "creation": "2025-07-30T13:45:06.948Z",
        "lastAccessed": "2025-07-30T13:45:06.948Z"
    },
    {
        "key": "xs",
        "value": "16%3AdkuR9MQN70lGjw%3A2%3A1753883098%3A-1%3A-1",
        "domain": "facebook.com",
        "path": "/",
        "hostOnly": false,
        "creation": "2025-07-30T13:45:06.948Z",
        "lastAccessed": "2025-07-30T13:45:06.948Z"
    },
    {
        "key": "fr",
        "value": "0zGgkqus4rhcDcA9R.AWfW1hDr4MXDdwQf3VmcOgJZP4zYlD_W2fbSO2w9T2kmyhOfl4A.Bogn_1..AAA.0.0.BoiiHf.AWcJiamj6xKlh9lct2FGWZqmFgs",
        "domain": "facebook.com",
        "path": "/",
        "hostOnly": false,
        "creation": "2025-07-30T13:45:06.948Z",
        "lastAccessed": "2025-07-30T13:45:06.948Z"
    },
    {
        "key": "wl_cbv",
        "value": "v2%3Bclient_version%3A2883%3Btimestamp%3A1753883103",
        "domain": "facebook.com",
        "path": "/",
        "hostOnly": false,
        "creation": "2025-07-30T13:45:06.948Z",
        "lastAccessed": "2025-07-30T13:45:06.948Z"
    },
    {
        "key": "fbl_st",
        "value": "101024570%3BT%3A29231385",
        "domain": "facebook.com",
        "path": "/",
        "hostOnly": false,
        "creation": "2025-07-30T13:45:06.948Z",
        "lastAccessed": "2025-07-30T13:45:06.948Z"
    }
]
